<author><surname>Cernea </surname><given-names>M.M.</given-names></author>, <title>Putting people first: Sociological variables in rural development</title>,<publisher> World Bank & Oxford University Press</publisher>,<other> Oxford-Washington</other>, <year>1985</year>, (<year>1991</year>).
<author><surname>Chakrabati </surname><given-names>A.</given-names></author>,<author> <surname>Dhar </surname><given-names>A.</given-names></author>, <title>Dislocation and Resettlement in Development: From third world to the world of the third</title>, <publisher>Routledge</publisher>,<other> Abingdon Oxon</other>, <year>2010</year>.
<editor>Hansen A.</editor>, <editor>Oliver-Smith A</editor>, (eds.), <title>Involuntary Migration and Resettlement: The Problems and Responses of Dislocated People</title>,<publisher> Westview Press</publisher>, <other>Boulder, Colorado</other>, <year>1982</year>.
<author><surname>Hart </surname><given-names>D.</given-names></author>, <title>The Volta River Project: A case study in politics and technology</title> , <publisher>Edinburgh University Press</publisher>, <other>Edinburgh</other>, <year>1980</year>.
<author><surname>Heggelund </surname><given-names>G.</given-names></author>, <title>Environment and resettlement politics in China: The Three Gorges Project</title>, <publisher>Ashgate Publishing Ltd.</publisher>, <other>London</other>, <year>2004</year>.
<author><surname>Holtzman </surname><given-names>S.B.</given-names></author>,<title> Living in limbo: Conflict-induced displacement in Europe and Central Asia</title>, <publisher>World Bank Publications</publisher>, <other>Washington</other>, <year>2004</year>.
<author><surname>Mahapatra </surname><given-names>L.K.</given-names></author>, <title>Resettlement, Impoverishment and Reconstruction in India: Development for the Deprived</title>, <publisher>Vikas Publishing House</publisher>, <other>New Delhi</other>, <year>1999</year>.
<author><surname>McDowell </surname><given-names>Ch.</given-names></author>,<title> Understanding impoverishment. The consequences of development-induced displacement</title>, <publisher>Berghahn Books</publisher>, <other>New York</other>, <year>1996</year>.
<editor>McDowell Ch.</editor>, <editor>Morrell G.</editor> (ed.), <title>Displacement Beyond Conflict. Challenges for the 21st century</title>, <publisher>Berghahn Books</publisher>,<other> New York</other>, <year>2010</year>.
<author><surname>Mehta</surname><given-names> L.</given-names></author>, <title>Displaced By Development: Confronting Marginalisation And Gender Injustice</title>, <publisher>SAGE Publications Ltd</publisher>, <other>New Delhi</other>, <year>2009</year>.
<author><surname>Oleschak </surname><given-names>R.</given-names></author>, <title>The international law of development-induced displacement</title>, <publisher>University of St. Gallen</publisher>, <other>St Gallen</other>, <year>2009</year>.
<author><surname>Oliver-Smith</surname> <given-names>A.</given-names></author>, <title>Defying Displacement. Grassroots Resistance and the Critique of Development</title>, <publisher>University of Texas Press</publisher>, <other>Houston</other>, <year>2010</year>.
<author><surname>Oliver-Smith</surname> <given-names>A.</given-names></author>, <title>Displacement, resistance and the critique of development. From the grass-roots to the global</title>,<other> Queen Elizabeth Refugees Centre, Oxford University, Oxford</other>, <year>2002</year>.
<author><surname>Penz</surname><given-names> P.</given-names></author>, <author><surname>Drydyk</surname><given-names> J.</given-names></author>, <author><surname>Bose </surname><given-names>P.S.</given-names></author>, <title>Displacement by Development: Ethics, Rights and Responsibilities</title>, <publisher>Cambridge University Press</publisher>, <other>Cambridge</other>, <year>2011</year>.
<author><surname>Phuong </surname><given-names>C.</given-names></author>,<title> The international protection of internally displaced persons</title>, <publisher>Cambridge University Press</publisher>, <other>Cambridge</other>, <year>2004</year>.
<editor>Piguet F.</editor>, <editor>Pankhurst A.</editor> (eds.),<title> Moving People in Ethiopia: Development, Displacement & the State (Eastern Africa Series)</title>, <publisher>James Currey</publisher>, <year>2009</year>.
<author><surname>Rahman </surname><given-names>K.N.</given-names></author>, <title>Adversities of development: A case study of involuntary resettlement</title>,<publisher> Academic Press and Publishers</publisher>, <year>2004</year>.
<author><surname>Terminski</surname><given-names> B.</given-names></author>, <title>Environmentally-Induced Displacement: Theoretical Frameworks and Current Challenges</title>, <source>CEDEM Research Paper</source>, <publisher>University of Liege</publisher>, <other>Liege</other>, Septemeber <year>2012</year>.
<author><surname>Thukral</surname><given-names> E</given-names></author>:, <title>Big Dams, Displaced Peoples: Rivers of Sorrow, Rivers of Joy</title>, <publisher>Sage Publications</publisher>, <other>New Delhi</other>, <year>1992</year>.
<author><surname>Wali</surname> <given-names>A.</given-names></author>, <title>Kilowatts and crisis: Hydroelectric power and social dislocation in eastern Panama</title>, <publisher>Westview Press</publisher>, <other>Boulder</other>, <year>1989</year>.
<author><surname>Weiss</surname> <given-names>T.G.</given-names></author>, <author><surname>Korn</surname> <given-names>D.A.</given-names></author>, <title>Internal displacement: conceptualization and its consequences</title>, <publisher>Taylor & Francis</publisher>, <other>London-New York</other>, <year>2006</year>.
<author><surname>Vandergeest</surname> <given-names>P.</given-names></author>, <author><surname>Bose</surname> <given-names>P.S.</given-names></author>, <author><surname>Idahosa</surname> <given-names>P</given-names>.</author>, <title>Development's displacements: Ecologies, economies, and cultures at risk</title>, <publisher>UBC Press</publisher>, <other>Vancouver</other>, <year>2007</year>.
<author><surname>Verma</surname> <given-names>M.K.</given-names></author>, <title>Development, displacement, and resettlement</title>, <publisher>Rawat Publications</publisher>, <other>New Delhi</other>, <year>2004</year>.
<author><surname>Vora</surname> <given-names>R.</given-names></author>, <title>World`s First Anti-Dam Movement: Mulshi Satyagraha 1920-1924</title>, <publisher>Orient Blackswan</publisher>, <other>New Delhi</other>, <year>2009</year>.
